assistants/__init__.py
assistants/examples/__init__.py
assistants/examples/code_assistant_data_visualization.py
assistants/examples/loan_estimate_assistant.py
assistants/examples/product_description_assistant.py
assistants/examples/summarize_assistant_operations.py
assistants/langregister/__init__.py
assistants/langregister/base.py
assistants/langregister/mongo_db_atlas.py
assistants/llm_assistants/__init__.py
assistants/llm_assistants/assistants.py
assistants/llm_assistants/openai_assistants.py
assistants/utils/__init__.py
assistants/utils/utilities.py
langassist-0.0.9.dist-info/LICENSE
langassist-0.0.9.dist-info/METADATA
langassist-0.0.9.dist-info/WHEEL
langassist-0.0.9.dist-info/top_level.txt
langassist-0.0.9.dist-info/RECORD
