Metadata-Version: 2.1
Name: langassist
Version: 0.0.9
Summary: The framework for language assistants
Author-email: Rajib Deb <rajib76.gcp@gmail.com>
Project-URL: Homepage, https://github.com/rajib76/assistants
Classifier: Programming Language :: Python :: 3
Classifier: License :: OSI Approved :: MIT License
Classifier: Operating System :: OS Independent
Requires-Python: >=3.10
License-File: LICENSE
Requires-Dist: openai
Requires-Dist: python-dotenv
Requires-Dist: requests
Requires-Dist: pymongo
